admin_api/__init__.py
admin_api/api_client.py
admin_api/auth_api.py
admin_api/configuration.py
admin_api/rest.py
admin_api/api/__init__.py
admin_api/api/app_token_api.py
admin_api/api/auto_generate_app_token_api.py
admin_api/models/__init__.py
admin_api/models/app_token.py
test/__init__.py
app_token_api-1.0.0.dist-info/METADATA
app_token_api-1.0.0.dist-info/WHEEL
app_token_api-1.0.0.dist-info/top_level.txt
app_token_api-1.0.0.dist-info/RECORD
