Metadata-Version: 2.1
Name: app-token-api
Version: 1.0.0
Summary: Hydrogen App Token API
Home-page: UNKNOWN
Author-email: info@hydrogenplatform.com
License: UNKNOWN
Keywords: Swagger,Hydrogen App Token API
Platform: UNKNOWN
Requires-Dist: certifi (>=2017.4.17)
Requires-Dist: python-dateutil (>=2.1)
Requires-Dist: six (>=1.10)
Requires-Dist: urllib3 (>=1.23)
